[
  {
    "name": "LENOVO TABLETTE ANDROID TAB M10 HD 10,1\" 32 GO (TB-X505L)",
    "price": 2040,
    "offers": 2,
    "url": "https://primini.ma/c/p/170958/Lenovo-Tablette-Android-Tab-M10-Hd-10-1-32-Go-Tb-X505l",
    "image": "https://cdn.primini.ma/250_lenovo-tablette-android-tab-m10-hd-10-1-32-go-tb-x505l-1.webp",
    "offers_details": [
      {
        "store_name": "Electromall",
        "store_url": "https://primini.ma/r/d/36/Electromall",
        "store_rating": 0,
        "product_title": "Lenovo TABLETTE M10 TB-X505L 10,1''",
        "price": 2040,
        "stock": null,
        "last_update": "03/10/2025",
        "offer_url": "https://primini.ma/gotostore/6355db2ef5dfed72799c9e41?clickarea=retailer&pagetype=product"
      }
    ],
    "offers_count": 1
  },
  {
    "name": "Apple iPad Air 4G LTE 256 Go 27,7 cm (10.9\") iOS 14 Gris",
    "price": 12449,
    "offers": 2,
    "url": "https://primini.ma/c/p/154589/Apple-I-Pad-Air-4g-Lte-256-Go-27-7-Cm-10-9-I-Os-14-Gris",
    "image": "https://cdn.primini.ma/250_0190199790278-apple-i-pad-air-4g-lte-256-go-27-7-cm-10-9-i-os-14-gris-1.webp",
    "offers_details": [
      {
        "store_name": "VIRGIN MEGASTORE",
        "store_url": "https://primini.ma/r/d/82/Virgin-Megastore",
        "store_rating": 0,
        "product_title": "iPad Air (2020) Wi-Fi + Cellular 256 Go - Gris Sidéral",
        "price": 12559,
        "stock": null,
        "last_update": "03/10/2025",
        "offer_url": "https://primini.ma/gotostore/666a1de7624098261afd2d72?clickarea=retailer&pagetype=product"
      }
    ],
    "offers_count": 1
  },
  {
    "name": "Microsoft Surface Pro 7 256 Go 31,2 cm (12.3\") 10e génération de processeurs 8 Go Windows 10 Pro Noir (PVR-00018)",
    "price": 16190,
    "offers": 2,
    "url": "https://primini.ma/c/p/150764/Microsoft-Surface-Pro-7-256-Go-31-2-Cm-12-3-10e-Generation-De-Processeurs-8-Go-Windows-10-Pro-Noir-Pvr-00018",
    "image": "https://cdn.primini.ma/250_889842501209-microsoft-surface-pro-7-256-go-31-2-cm-12-3-10e-generation-de-processeurs-8-go-windows-10-pro-noir-pvr-00018-1.webp",
    "offers_details": [
      {
        "store_name": "DistriComputer",
        "store_url": "https://primini.ma/r/d/32/Distri-Computer",
        "store_rating": 0,
        "product_title": "MICROSOFT SURFACE PRO 7 I5-8GB-256GBSSD-WIN10 PRO +Clavier+Stylet+Souris",
        "price": 16190,
        "stock": null,
        "last_update": "03/10/2025",
        "offer_url": "https://primini.ma/gotostore/65df40acb79534345659bfed?clickarea=retailer&pagetype=product"
      },
      {
        "store_name": "Technoplace",
        "store_url": "https://primini.ma/r/d/1/Technoplace",
        "store_rating": 0,
        "product_title": "MICROSOFT SURFACE PRO 7 I5",
        "price": 17988,
        "stock": null,
        "last_update": "03/10/2025",
        "offer_url": "https://primini.ma/gotostore/65d925cd472ca713907e01b9?clickarea=retailer&pagetype=product"
      }
    ],
    "offers_count": 2
  },
  {
    "name": "Apple iPad Pro 128 Go 32,8 cm (12.9\") Apple M 8 Go Wi-Fi 6E (802.11ax) iPadOS 16 Argent",
    "price": 12990,
    "offers": 2,
    "url": "https://primini.ma/c/p/150139/Apple-I-Pad-Pro-128-Go-32-8-Cm-12-9-Apple-M-8-Go-Wi-Fi-6e-802-11ax-I-Pad-Os-16-Argent",
    "image": "https://cdn.primini.ma/250_apple-i-pad-pro-128-go-32-8-cm-12-9-apple-m-8-go-wi-fi-6e-802-11ax-i-pad-os-16-argent-1.webp",
    "offers_details": [
      {
        "store_name": "VIRGIN MEGASTORE",
        "store_url": "https://primini.ma/r/d/82/Virgin-Megastore",
        "store_rating": 0,
        "product_title": "iPad Pro 12.9-Inch M2 WI-FI 128Go - Space Grey",
        "price": 17690,
        "stock": null,
        "last_update": "03/10/2025",
        "offer_url": "https://primini.ma/gotostore/63ef83f721edb618ddcdcb74?clickarea=retailer&pagetype=product"
      }
    ],
    "offers_count": 1
  },
  {
    "name": "Apple iPad Pro 256 Go 32,8 cm (12.9\") Apple M 8 Go Wi-Fi 6E (802.11ax) iPadOS 16 Argent",
    "price": 14490,
    "offers": 2,
    "url": "https://primini.ma/c/p/150138/Apple-I-Pad-Pro-256-Go-32-8-Cm-12-9-Apple-M-8-Go-Wi-Fi-6e-802-11ax-I-Pad-Os-16-Argent",
    "image": "https://cdn.primini.ma/250_apple-i-pad-pro-256-go-32-8-cm-12-9-apple-m-8-go-wi-fi-6e-802-11ax-i-pad-os-16-argent-1.webp",
    "offers_details": [
      {
        "store_name": "VIRGIN MEGASTORE",
        "store_url": "https://primini.ma/r/d/82/Virgin-Megastore",
        "store_rating": 0,
        "product_title": "iPad Pro 12.9-Inch M2 WI-FI 256Go - Silver",
        "price": 19290,
        "stock": null,
        "last_update": "03/10/2025",
        "offer_url": "https://primini.ma/gotostore/63ef83f721edb618ddcdcb71?clickarea=retailer&pagetype=product"
      }
    ],
    "offers_count": 1
  },
  {
    "name": "Apple iPad Pro 256 Go 32,8 cm (12.9\") Apple M 8 Go Wi-Fi 6E (802.11ax) iPadOS 16 Gris",
    "price": 14190,
    "offers": 2,
    "url": "https://primini.ma/c/p/150137/Apple-I-Pad-Pro-256-Go-32-8-Cm-12-9-Apple-M-8-Go-Wi-Fi-6e-802-11ax-I-Pad-Os-16-Gris",
    "image": "https://cdn.primini.ma/250_apple-i-pad-pro-256-go-32-8-cm-12-9-apple-m-8-go-wi-fi-6e-802-11ax-i-pad-os-16-gris-1.webp",
    "offers_details": [
      {
        "store_name": "VIRGIN MEGASTORE",
        "store_url": "https://primini.ma/r/d/82/Virgin-Megastore",
        "store_rating": 0,
        "product_title": "iPad Pro 12.9-Inch M2 WI-FI 256Go - Space Grey",
        "price": 20550,
        "stock": null,
        "last_update": "03/10/2025",
        "offer_url": "https://primini.ma/gotostore/63ef83f721edb618ddcdcb70?clickarea=retailer&pagetype=product"
      }
    ],
    "offers_count": 1
  },
  {
    "name": "Apple iPad Pro 128 Go 32,8 cm (12.9\") Apple M 8 Go Wi-Fi 6E (802.11ax) iPadOS 16 Gris",
    "price": 12939,
    "offers": 2,
    "url": "https://primini.ma/c/p/150136/Apple-I-Pad-Pro-128-Go-32-8-Cm-12-9-Apple-M-8-Go-Wi-Fi-6e-802-11ax-I-Pad-Os-16-Gris",
    "image": "https://cdn.primini.ma/250_apple-i-pad-pro-128-go-32-8-cm-12-9-apple-m-8-go-wi-fi-6e-802-11ax-i-pad-os-16-gris-1.webp",
    "offers_details": [
      {
        "store_name": "VIRGIN MEGASTORE",
        "store_url": "https://primini.ma/r/d/82/Virgin-Megastore",
        "store_rating": 0,
        "product_title": "iPad Pro 12.9-Inch M2 WI-FI 128Go - Silver",
        "price": 17690,
        "stock": null,
        "last_update": "03/10/2025",
        "offer_url": "https://primini.ma/gotostore/666a1dea624098261afd2fe2?clickarea=retailer&pagetype=product"
      }
    ],
    "offers_count": 1
  },
  {
    "name": "Apple iPad Pro 5G LTE 128 Go 27,9 cm (11\") Apple M 8 Go Wi-Fi 6E (802.11ax) iPadOS 16 Gris",
    "price": 13190,
    "offers": 2,
    "url": "https://primini.ma/c/p/150135/Apple-I-Pad-Pro-5g-Lte-128-Go-27-9-Cm-11-Apple-M-8-Go-Wi-Fi-6e-802-11ax-I-Pad-Os-16-Gris",
    "image": "https://cdn.primini.ma/250_apple-i-pad-pro-5g-lte-128-go-27-9-cm-11-apple-m-8-go-wi-fi-6e-802-11ax-i-pad-os-16-gris-1.webp",
    "offers_details": [
      {
        "store_name": "Micromad",
        "store_url": "https://primini.ma/r/d/87/Micromad",
        "store_rating": 0,
        "product_title": "iPad Pro 11 Pouces (Puce M2) - Tablette - MICROMAD #1 Boutique Hightech",
        "price": 14509,
        "stock": null,
        "last_update": "03/10/2025",
        "offer_url": "https://primini.ma/gotostore/659a889c5ed242f557cb9ddd?clickarea=retailer&pagetype=product"
      }
    ],
    "offers_count": 1
  },
  {
    "name": "Apple iPad 64 Go 27,7 cm (10.9\") Wi-Fi 6 (802.11ax) iPadOS 16 Argent",
    "price": 5990,
    "offers": 2,
    "url": "https://primini.ma/c/p/150134/Apple-I-Pad-64-Go-27-7-Cm-10-9-Wi-Fi-6-802-11ax-I-Pad-Os-16-Argent",
    "image": "https://cdn.primini.ma/250_apple-i-pad-64-go-27-7-cm-10-9-wi-fi-6-802-11ax-i-pad-os-16-argent-1.webp",
    "offers_details": [
      {
        "store_name": "Fournipro.ma",
        "store_url": "https://primini.ma/r/d/7/Fournipro-Ma",
        "store_rating": 0,
        "product_title": "TABLETTE APPLE IPAD 10,9\" 64GO WIFI 10ᵉ GÉNÉRATION ARGENT (MPQ03NF/A)",
        "price": 4940,
        "stock": null,
        "last_update": "03/10/2025",
        "offer_url": "https://primini.ma/gotostore/6752277070b0c9c2ef6738f8?clickarea=retailer&pagetype=product"
      },
      {
        "store_name": "VIRGIN MEGASTORE",
        "store_url": "https://primini.ma/r/d/82/Virgin-Megastore",
        "store_rating": 0,
        "product_title": "iPad 10.9-Inch Wi-Fi 64Go - Silver",
        "price": 5290,
        "stock": null,
        "last_update": "03/10/2025",
        "offer_url": "https://primini.ma/gotostore/63ef83f721edb618ddcdcb6d?clickarea=retailer&pagetype=product"
      }
    ],
    "offers_count": 2
  },
  {
    "name": "Apple iPad Pro 128 Go 27,9 cm (11\") Apple M 8 Go Wi-Fi 6E (802.11ax) iPadOS 16 Gris",
    "price": 12990,
    "offers": 2,
    "url": "https://primini.ma/c/p/150133/Apple-I-Pad-Pro-128-Go-27-9-Cm-11-Apple-M-8-Go-Wi-Fi-6e-802-11ax-I-Pad-Os-16-Gris",
    "image": "https://cdn.primini.ma/250_apple-i-pad-pro-128-go-27-9-cm-11-apple-m-8-go-wi-fi-6e-802-11ax-i-pad-os-16-gris-1.webp",
    "offers_details": [
      {
        "store_name": "VIRGIN MEGASTORE",
        "store_url": "https://primini.ma/r/d/82/Virgin-Megastore",
        "store_rating": 0,
        "product_title": "iPad Pro 11-Inch Wi-Fi 128Go - Space Grey",
        "price": 12990,
        "stock": null,
        "last_update": "03/10/2025",
        "offer_url": "https://primini.ma/gotostore/63ef83f721edb618ddcdcb6c?clickarea=retailer&pagetype=product"
      }
    ],
    "offers_count": 1
  },
  {
    "name": "Apple iPad 64 Go 27,7 cm (10.9\") Bleu",
    "price": 5990,
    "offers": 2,
    "url": "https://primini.ma/c/p/150132/Apple-I-Pad-64-Go-27-7-Cm-10-9-Bleu",
    "image": "https://cdn.primini.ma/250_0194253387732%20-apple-i-pad-64-go-27-7-cm-10-9-bleu-1.webp",
    "offers_details": [
      {
        "store_name": "Fournipro.ma",
        "store_url": "https://primini.ma/r/d/7/Fournipro-Ma",
        "store_rating": 0,
        "product_title": "TABLETTE APPLE IPAD 10,9\" 64GO WIFI 10ᵉ GÉNÉRATION BLEU (MPQ13NF/A)",
        "price": 4940,
        "stock": null,
        "last_update": "03/10/2025",
        "offer_url": "https://primini.ma/gotostore/6752277070b0c9c2ef6738f6?clickarea=retailer&pagetype=product"
      },
      {
        "store_name": "VIRGIN MEGASTORE",
        "store_url": "https://primini.ma/r/d/82/Virgin-Megastore",
        "store_rating": 0,
        "product_title": "iPad 10.9-Inch Wi-Fi 64Go - Blue",
        "price": 5290,
        "stock": null,
        "last_update": "03/10/2025",
        "offer_url": "https://primini.ma/gotostore/63ef83f721edb618ddcdcb6b?clickarea=retailer&pagetype=product"
      }
    ],
    "offers_count": 2
  },
  {
    "name": "Apple iPad Pro 5G LTE 256 Go 27,9 cm (11\") Apple M 8 Go Wi-Fi 6E (802.11ax) iPadOS 16 Gris",
    "price": 14900,
    "offers": 2,
    "url": "https://primini.ma/c/p/150131/Apple-I-Pad-Pro-5g-Lte-256-Go-27-9-Cm-11-Apple-M-8-Go-Wi-Fi-6e-802-11ax-I-Pad-Os-16-Gris",
    "image": "https://cdn.primini.ma/250_apple-i-pad-pro-5g-lte-256-go-27-9-cm-11-apple-m-8-go-wi-fi-6e-802-11ax-i-pad-os-16-gris-1.webp",
    "offers_details": [
      {
        "store_name": "Micromad",
        "store_url": "https://primini.ma/r/d/87/Micromad",
        "store_rating": 0,
        "product_title": "iPad Pro 11 Pouces (Puce M2) - Tablette - MICROMAD #1 Boutique Hightech",
        "price": 16390,
        "stock": null,
        "last_update": "03/10/2025",
        "offer_url": "https://primini.ma/gotostore/659a889c5ed242f557cb9de1?clickarea=retailer&pagetype=product"
      },
      {
        "store_name": "VIRGIN MEGASTORE",
        "store_url": "https://primini.ma/r/d/82/Virgin-Megastore",
        "store_rating": 0,
        "product_title": "iPad Pro 11-Inch Wi-Fi + Cellular 256Go - Space Grey",
        "price": 16890,
        "stock": null,
        "last_update": "03/10/2025",
        "offer_url": "https://primini.ma/gotostore/63ef83f721edb618ddcdcb6a?clickarea=retailer&pagetype=product"
      }
    ],
    "offers_count": 2
  },
  {
    "name": "Apple iPad 256 Go 27,7 cm (10.9\") Wi-Fi 6 (802.11ax) iPadOS 16 Argent",
    "price": 8990,
    "offers": 2,
    "url": "https://primini.ma/c/p/150130/Apple-I-Pad-256-Go-27-7-Cm-10-9-Wi-Fi-6-802-11ax-I-Pad-Os-16-Argent",
    "image": "https://cdn.primini.ma/250_apple-i-pad-256-go-27-7-cm-10-9-wi-fi-6-802-11ax-i-pad-os-16-argent-1.webp",
    "offers_details": [
      {
        "store_name": "VIRGIN MEGASTORE",
        "store_url": "https://primini.ma/r/d/82/Virgin-Megastore",
        "store_rating": 0,
        "product_title": "iPad 10.9-Inch Wi-Fi 256Go - Silver",
        "price": 6999,
        "stock": null,
        "last_update": "03/10/2025",
        "offer_url": "https://primini.ma/gotostore/63ef83f721edb618ddcdcb69?clickarea=retailer&pagetype=product"
      }
    ],
    "offers_count": 1
  },
  {
    "name": "Apple iPad 256 Go 27,7 cm (10.9\") Wi-Fi 6 (802.11ax) iPadOS 16 Bleu",
    "price": 8990,
    "offers": 2,
    "url": "https://primini.ma/c/p/150129/Apple-I-Pad-256-Go-27-7-Cm-10-9-Wi-Fi-6-802-11ax-I-Pad-Os-16-Bleu",
    "image": "https://cdn.primini.ma/250_apple-i-pad-256-go-27-7-cm-10-9-wi-fi-6-802-11ax-i-pad-os-16-bleu-1.webp",
    "offers_details": [],
    "offers_count": 0
  },
  {
    "name": "Apple iPad 5G TD-LTE & FDD-LTE 64 Go 27,7 cm (10.9\") Wi-Fi 6 (802.11ax) iPadOS 16 Argent",
    "price": 8990,
    "offers": 2,
    "url": "https://primini.ma/c/p/150094/Apple-I-Pad-5g-Td-Lte-Fdd-Lte-64-Go-27-7-Cm-10-9-Wi-Fi-6-802-11ax-I-Pad-Os-16-Argent",
    "image": "https://cdn.primini.ma/250_apple-i-pad-5g-td-lte-fdd-lte-64-go-27-7-cm-10-9-wi-fi-6-802-11ax-i-pad-os-16-argent-1.webp",
    "offers_details": [
      {
        "store_name": "Fournipro.ma",
        "store_url": "https://primini.ma/r/d/7/Fournipro-Ma",
        "store_rating": 0,
        "product_title": "TABLETTE APPLE IPAD WI-FI CELLULAIRE 27,7 CM (10.9\") 2360 X 1640 PIXELS LED IPS 64 GO ARGENT (MQ6J3NF/A)",
        "price": 6790,
        "stock": null,
        "last_update": "04/10/2025",
        "offer_url": "https://primini.ma/gotostore/66f730fa331af89aeb3e422e?clickarea=retailer&pagetype=product"
      },
      {
        "store_name": "VIRGIN MEGASTORE",
        "store_url": "https://primini.ma/r/d/82/Virgin-Megastore",
        "store_rating": 0,
        "product_title": "iPad 10.9-Inch Wi-Fi + Cellular 64Go - Silver",
        "price": 7749,
        "stock": null,
        "last_update": "03/10/2025",
        "offer_url": "https://primini.ma/gotostore/63ef83ea21edb618ddcdc5bc?clickarea=retailer&pagetype=product"
      }
    ],
    "offers_count": 2
  },
  {
    "name": "Apple iPad 4G LTE 64 Go 25,9 cm (10.2\") Wi-Fi 5 (802.11ac) iPadOS 15 Argent",
    "price": 5990,
    "offers": 2,
    "url": "https://primini.ma/c/p/150093/Apple-I-Pad-4g-Lte-64-Go-25-9-Cm-10-2-Wi-Fi-5-802-11ac-I-Pad-Os-15-Argent",
    "image": "https://cdn.primini.ma/250_apple-i-pad-4g-lte-64-go-25-9-cm-10-2-wi-fi-5-802-11ac-i-pad-os-15-argent-1.webp",
    "offers_details": [
      {
        "store_name": "VIRGIN MEGASTORE",
        "store_url": "https://primini.ma/r/d/82/Virgin-Megastore",
        "store_rating": 0,
        "product_title": "iPad 10.2\" - Inch WI-FI + Cellular 64 Go - Silver",
        "price": 7390,
        "stock": null,
        "last_update": "03/10/2025",
        "offer_url": "https://primini.ma/gotostore/666a1de7624098261afd2d32?clickarea=retailer&pagetype=product"
      }
    ],
    "offers_count": 1
  },
  {
    "name": "Samsung Tablette tab S7 8Go 256Go Noir (",
    "price": 9900,
    "offers": 3,
    "url": "https://primini.ma/c/p/144554/Samsung-Tablette-Tab-S7-8go-256go-Noir",
    "image": "https://cdn.primini.ma/250_samsung-tablette-tab-s7-8go-256go-noir-1.webp",
    "offers_details": [
      {
        "store_name": "Technoplace",
        "store_url": "https://primini.ma/r/d/1/Technoplace",
        "store_rating": 0,
        "product_title": "Samsung Tablette Tab S7+ 12,4 \" Octa Core 8Go 256Go Android 4G 8 Mp 13 Mp Noir.",
        "price": 10120,
        "stock": null,
        "last_update": "03/10/2025",
        "offer_url": "https://primini.ma/gotostore/65d925ca472ca713907dfbf8?clickarea=retailer&pagetype=product"
      }
    ],
    "offers_count": 1
  },
  {
    "name": "Tablette Galaxy S8 Ultra (16+512GB) Graphite (",
    "price": 12491.67,
    "offers": 12,
    "url": "https://primini.ma/c/p/144542/Tablette-Galaxy-S8-Ultra-16-512gb-Graphite",
    "image": "https://cdn.primini.ma/250_8806094194746-tablette-galaxy-s8-ultra-16-512gb-graphite-1.webp",
    "offers_details": [
      {
        "store_name": "Electromall",
        "store_url": "https://primini.ma/r/d/36/Electromall",
        "store_rating": 0,
        "product_title": "Recommandez Tablette Galaxy S8 Ultra (16+512GB) Graphite SM-X906BZAFMWD",
        "price": 14900,
        "stock": null,
        "last_update": "03/10/2025",
        "offer_url": "https://primini.ma/gotostore/6355db2ef5dfed72799c9e3d?clickarea=retailer&pagetype=product"
      },
      {
        "store_name": "DistriComputer",
        "store_url": "https://primini.ma/r/d/32/Distri-Computer",
        "store_rating": 0,
        "product_title": "Tablette Samsung Galaxy Tab S8 Ultra 5G (16GB / 512Go)",
        "price": 15440,
        "stock": null,
        "last_update": "03/10/2025",
        "offer_url": "https://primini.ma/gotostore/65df40acb79534345659bf9d?clickarea=retailer&pagetype=product"
      },
      {
        "store_name": "Technoplace",
        "store_url": "https://primini.ma/r/d/1/Technoplace",
        "store_rating": 0,
        "product_title": "SAMSUNG Tablette Tab S8Ultra Noir 146\" Octa Core 16Go 512Go Android 5G 12Mpx 12Mpx 13Mpx 6Mpx 12M (SM-X906BZAFMWD)",
        "price": 15440.4,
        "stock": null,
        "last_update": "03/10/2025",
        "offer_url": "https://primini.ma/gotostore/65d925ca472ca713907dfc1a?clickarea=retailer&pagetype=product"
      },
      {
        "store_name": "Network Service Info",
        "store_url": "https://primini.ma/r/d/8/Network-Service-Info",
        "store_rating": 0,
        "product_title": "Tablette Samsung Galaxy Tab S8 Ultra 5G (16GB / 512Go)(SM-X906BZAFMWD)",
        "price": 16440,
        "stock": null,
        "last_update": "04/10/2025",
        "offer_url": "https://primini.ma/gotostore/66269c903c7b0245abc609f9?clickarea=retailer&pagetype=product"
      },
      {
        "store_name": "Iris.ma",
        "store_url": "https://primini.ma/r/d/3/Iris",
        "store_rating": 5,
        "product_title": "Tablette Samsung Galaxy Tab S8 Ultra 5G (16GB / 512Go)",
        "price": 16440,
        "stock": null,
        "last_update": "03/10/2025",
        "offer_url": "https://primini.ma/gotostore/6351a3f755f61019978c63de?clickarea=retailer&pagetype=product"
      }
    ],
    "offers_count": 5
  },
  {
    "name": "Samsung Galaxy Tab A7 Lite 8.7\" 32 Go Gris 4G (",
    "price": 1457.5,
    "offers": 10,
    "url": "https://primini.ma/c/p/144541/Samsung-Galaxy-Tab-A7-Lite-8-7-32-Go-Gris-4g",
    "image": "https://cdn.primini.ma/250_8806092268098-samsung-galaxy-tab-a7-lite-8-7-32-go-gris-4g-1.webp",
    "offers_details": [
      {
        "store_name": "VIRGIN MEGASTORE",
        "store_url": "https://primini.ma/r/d/82/Virgin-Megastore",
        "store_rating": 0,
        "product_title": "Tablette Galaxy Tab A7 Lite 32 Go - Grey",
        "price": 890,
        "stock": null,
        "last_update": "03/10/2025",
        "offer_url": "https://primini.ma/gotostore/666f63d94433e77e1b54686e?clickarea=retailer&pagetype=product"
      },
      {
        "store_name": "Technoplace",
        "store_url": "https://primini.ma/r/d/1/Technoplace",
        "store_rating": 0,
        "product_title": "SAMSUNG Tablette A7 Lite 8,7\" 3Go Octa Core 32Go Android 4G 2 Mpx 2 Mpx 8 Mpx Gray (SM-T225NZALMWD)",
        "price": 1693.2,
        "stock": null,
        "last_update": "03/10/2025",
        "offer_url": "https://primini.ma/gotostore/65d925d2472ca713907e0ae5?clickarea=retailer&pagetype=product"
      },
      {
        "store_name": "NGT",
        "store_url": "https://primini.ma/r/d/23/Ngt",
        "store_rating": 0,
        "product_title": "SAMSUNG Tablette A7 lite 8,7\" 3Go Octa Core 32Go Android 4G (SM-T225NZALMWD)",
        "price": 1990,
        "stock": null,
        "last_update": "03/10/2025",
        "offer_url": "https://primini.ma/gotostore/63545cdb867d3633dfdd45a4?clickarea=retailer&pagetype=product"
      }
    ],
    "offers_count": 3
  },
  {
    "name": "Samsung Galaxy Tab S8 8 Go 128 Go (",
    "price": 7491.66,
    "offers": 8,
    "url": "https://primini.ma/c/p/144540/Samsung-Galaxy-Tab-S8-8-Go-128-Go",
    "image": "https://cdn.primini.ma/250_8806094200041-samsung-galaxy-tab-s8-8-go-128-go-1.webp",
    "offers_details": [
      {
        "store_name": "Electromall",
        "store_url": "https://primini.ma/r/d/36/Electromall",
        "store_rating": 0,
        "product_title": "Recommandez Tablette Samsung  Galaxy S8 (8+128GB) Graphite SM-X706BZAAMWD",
        "price": 8900,
        "stock": null,
        "last_update": "03/10/2025",
        "offer_url": "https://primini.ma/gotostore/6355db2ef5dfed72799c9e3c?clickarea=retailer&pagetype=product"
      },
      {
        "store_name": "VIRGIN MEGASTORE",
        "store_url": "https://primini.ma/r/d/82/Virgin-Megastore",
        "store_rating": 0,
        "product_title": "Tablette Galaxy Tab S8 8Go RAM 128 Go - Graphite",
        "price": 8990,
        "stock": null,
        "last_update": "03/10/2025",
        "offer_url": "https://primini.ma/gotostore/63ef83ec21edb618ddcdc68c?clickarea=retailer&pagetype=product"
      },
      {
        "store_name": "Technoplace",
        "store_url": "https://primini.ma/r/d/1/Technoplace",
        "store_rating": 0,
        "product_title": "SAMSUNG Tablette Tab S8 Gris Graphite 11\" Octa Core 8Go 128Go Android 5G 12Mpx 13Mpx 6Mpx 12M (SM-X706BZAAMWD)",
        "price": 9253.2,
        "stock": null,
        "last_update": "03/10/2025",
        "offer_url": "https://primini.ma/gotostore/65d925ca472ca713907dfbf9?clickarea=retailer&pagetype=product"
      }
    ],
    "offers_count": 3
  },
  {
    "name": "Tablette Samsung Galaxy Tab S8 + 8Gb,256Go Pink Gold Silver (",
    "price": 9795.23,
    "offers": 12,
    "url": "https://primini.ma/c/p/144445/Tablette-Samsung-Galaxy-Tab-S8-8gb-256go-Pink-Gold-Silver",
    "image": "https://cdn.primini.ma/250_8806094198249-tablette-samsung-galaxy-tab-s8-8gb-256go-pink-gold-silver-1.webp",
    "offers_details": [
      {
        "store_name": "Fournipro.ma",
        "store_url": "https://primini.ma/r/d/7/Fournipro-Ma",
        "store_rating": 0,
        "product_title": "Tablette Tactile SAMSUNG Galaxy Tab S8 PLUS 12.4\" 8G  256GB Silver (SM-X806BZSBMWD)",
        "price": 9340,
        "stock": null,
        "last_update": "03/10/2025",
        "offer_url": "https://primini.ma/gotostore/63593d86ae98c3d2cf64ba85?clickarea=retailer&pagetype=product"
      },
      {
        "store_name": "Electromall",
        "store_url": "https://primini.ma/r/d/36/Electromall",
        "store_rating": 0,
        "product_title": "Precommandez Tablette Galaxy S8+ (8+256GB) Pink Gold SM-X806BIDBMWD",
        "price": 11400,
        "stock": null,
        "last_update": "03/10/2025",
        "offer_url": "https://primini.ma/gotostore/6355db2ef5dfed72799c9e40?clickarea=retailer&pagetype=product"
      },
      {
        "store_name": "Technoplace",
        "store_url": "https://primini.ma/r/d/1/Technoplace",
        "store_rating": 0,
        "product_title": "SAMSUNG Tablette Tab S8+ Pink Gold 124\" Octa Core 8Go 256Go Android 5G 12Mpx 13Mpx 6Mpx 12M (SM-X806BIDBMWD)",
        "price": 11587.2,
        "stock": null,
        "last_update": "03/10/2025",
        "offer_url": "https://primini.ma/gotostore/65d925ce472ca713907e032a?clickarea=retailer&pagetype=product"
      },
      {
        "store_name": "Micromad",
        "store_url": "https://primini.ma/r/d/87/Micromad",
        "store_rating": 0,
        "product_title": "Samsung Galaxy Tab S8 Plus - Tablette - MICROMAD #1 Boutique Hightech",
        "price": 11603.9,
        "stock": null,
        "last_update": "03/10/2025",
        "offer_url": "https://primini.ma/gotostore/659a889f5ed242f557cba440?clickarea=retailer&pagetype=product"
      },
      {
        "store_name": "DistriComputer",
        "store_url": "https://primini.ma/r/d/32/Distri-Computer",
        "store_rating": 0,
        "product_title": "Tablette Samsung Galaxy Tab S8+ 5G (8GB / 256Go)",
        "price": 11830,
        "stock": null,
        "last_update": "03/10/2025",
        "offer_url": "https://primini.ma/gotostore/66269cb23c7b0245abc632bf?clickarea=retailer&pagetype=product"
      },
      {
        "store_name": "Network Service Info",
        "store_url": "https://primini.ma/r/d/8/Network-Service-Info",
        "store_rating": 0,
        "product_title": "Tablette Samsung Galaxy Tab S8+ 5G (8GB / 256Go)(SM-X806BIDBMWD)",
        "price": 12600,
        "stock": null,
        "last_update": "23/09/2025",
        "offer_url": "https://primini.ma/gotostore/66269c903c7b0245abc609e5?clickarea=retailer&pagetype=product"
      }
    ],
    "offers_count": 6
  },
  {
    "name": "Samsung Galaxy A7 lite 8,7\" 3Go Octa Core 32Go Android 4G 2 Mpx 2 Mpx 8 Mpx Silver.",
    "price": 1457.5,
    "offers": 6,
    "url": "https://primini.ma/c/p/144442/Samsung-Galaxy-A7-Lite-8-7-3go-Octa-Core-32go-Android-4g-2-Mpx-2-Mpx-8-Mpx-Silver",
    "image": "https://primini.ma/images/placeholder.jpg",
    "offers_details": [
      {
        "store_name": "VIRGIN MEGASTORE",
        "store_url": "https://primini.ma/r/d/82/Virgin-Megastore",
        "store_rating": 0,
        "product_title": "Tablette Galaxy Tab A7 Lite 32 Go - Silver",
        "price": 890,
        "stock": null,
        "last_update": "03/10/2025",
        "offer_url": "https://primini.ma/gotostore/666a1de7624098261afd2cb1?clickarea=retailer&pagetype=product"
      },
      {
        "store_name": "Technoplace",
        "store_url": "https://primini.ma/r/d/1/Technoplace",
        "store_rating": 0,
        "product_title": "SAMSUNG Tablette A7 Lite 8,7\" 3Go Octa Core 32Go Android 4G 2 Mpx 2 Mpx 8 Mpx Silver (SM-T225NZSLMWD)",
        "price": 1693.2,
        "stock": null,
        "last_update": "03/10/2025",
        "offer_url": "https://primini.ma/gotostore/65d925ca472ca713907dfc14?clickarea=retailer&pagetype=product"
      },
      {
        "store_name": "Electromall",
        "store_url": "https://primini.ma/r/d/36/Electromall",
        "store_rating": 0,
        "product_title": "Samsung Tablette A7 8,7″ lite Octa Core 3Go 32Go (SM-T225NZSLMWD)",
        "price": 1840,
        "stock": null,
        "last_update": "03/10/2025",
        "offer_url": "https://primini.ma/gotostore/6355db2ef5dfed72799c9e37?clickarea=retailer&pagetype=product"
      },
      {
        "store_name": "Iris.ma",
        "store_url": "https://primini.ma/r/d/3/Iris",
        "store_rating": 5,
        "product_title": "Tablette Samsung Galaxy A7 Lite 3 GB",
        "price": 2269,
        "stock": null,
        "last_update": "03/10/2025",
        "offer_url": "https://primini.ma/gotostore/6351a3f755f61019978c63dc?clickarea=retailer&pagetype=product"
      }
    ],
    "offers_count": 4
  },
  {
    "name": "Samsung Galaxy Tab S4G LTE 16 Go 26,7 cm (10.5\") 3 Go Android Blanc",
    "price": 5990,
    "offers": 2,
    "url": "https://primini.ma/c/p/144240/Samsung-Galaxy-Tab-S4g-Lte-16-Go-26-7-Cm-10-5-3-Go-Android-Blanc",
    "image": "https://cdn.primini.ma/250_samsung-galaxy-tab-s4g-lte-16-go-26-7-cm-10-5-3-go-android-blanc-1.webp",
    "offers_details": [
      {
        "store_name": "Technoplace",
        "store_url": "https://primini.ma/r/d/1/Technoplace",
        "store_rating": 0,
        "product_title": "Tablette 3G/ 4G LTE Samsung Galaxy Tab S 10.5\" - 16 GB Android 4.4.2 KitKat",
        "price": 6400,
        "stock": null,
        "last_update": "03/10/2025",
        "offer_url": "https://primini.ma/gotostore/65d925c6472ca713907df6e4?clickarea=retailer&pagetype=product"
      }
    ],
    "offers_count": 1
  },
  {
    "name": "Apple iPad 64 Go 25,9 cm (10.2\") Argent",
    "price": 4125,
    "offers": 2,
    "url": "https://primini.ma/c/p/143892/Apple-I-Pad-64-Go-25-9-Cm-10-2-Argent",
    "image": "https://cdn.primini.ma/250_0194252515945%20-apple-i-pad-64-go-25-9-cm-10-2-argent-1.webp",
    "offers_details": [
      {
        "store_name": "VIRGIN MEGASTORE",
        "store_url": "https://primini.ma/r/d/82/Virgin-Megastore",
        "store_rating": 0,
        "product_title": "iPad 10.2\" - Inch WI-FI 64Go - Silver",
        "price": 5390,
        "stock": null,
        "last_update": "03/10/2025",
        "offer_url": "https://primini.ma/gotostore/666a1de7624098261afd2d2f?clickarea=retailer&pagetype=product"
      }
    ],
    "offers_count": 1
  },
  {
    "name": "HP ElitePad Tabletă 1000 G2 3G 64 Go 25,6 cm (10.1\") Intel Atom® 4 Go Wi-Fi 4 (802.11n) Windows 8.1 Argent",
    "price": 9790.44,
    "offers": 2,
    "url": "https://primini.ma/c/p/143668/Hp-Elite-Pad-Tableta-1000-G2-3g-64-Go-25-6-Cm-10-1-Intel-Atom-R-4-Go-Wi-Fi-4-802-11n-Windows-8-1-Argent",
    "image": "https://cdn.primini.ma/250_0888793647622%20-hp-elite-pad-tableta-1000-g2-3g-64-go-25-6-cm-10-1-intel-atom-r-4-go-wi-fi-4-802-11n-windows-8-1-argent-1.webp",
    "offers_details": [],
    "offers_count": 0
  },
  {
    "name": "Apple - iPad Pro (2021) - 11'' - WiFi - 128 Go - Gris Sidéral",
    "price": 11300,
    "offers": 2,
    "url": "https://primini.ma/c/p/142898/Apple-I-Pad-Pro-2021-11-Wi-Fi-128-Go-Gris-Sideral",
    "image": "https://cdn.primini.ma/250_0194252185377-apple-i-pad-pro-2021-11-wi-fi-128-go-gris-sideral-1.webp",
    "offers_details": [
      {
        "store_name": "VIRGIN MEGASTORE",
        "store_url": "https://primini.ma/r/d/82/Virgin-Megastore",
        "store_rating": 0,
        "product_title": "iPad Pro (2021) 11\" Wi-Fi 128Go - Space Grey",
        "price": 11300,
        "stock": null,
        "last_update": "03/10/2025",
        "offer_url": "https://primini.ma/gotostore/666a1de7624098261afd2cbd?clickarea=retailer&pagetype=product"
      }
    ],
    "offers_count": 1
  },
  {
    "name": "Microsoft Surface Pro 7 128 Go 31,2 cm (12.3\") Intel® Core™ i3 4 Go Windows 10 Home Platine",
    "price": 6600,
    "offers": 4,
    "url": "https://primini.ma/c/p/142383/Microsoft-Surface-Pro-7-128-Go-31-2-Cm-12-3-Intel-R-Core-I3-4-Go-Windows-10-Home-Platine",
    "image": "https://cdn.primini.ma/250_0889842497175-microsoft-surface-pro-7-128-go-31-2-cm-12-3-intel-r-core-i3-4-go-windows-10-home-platine-4.webp",
    "offers_details": [
      {
        "store_name": "Tera",
        "store_url": "https://primini.ma/r/d/65/Tera",
        "store_rating": 0,
        "product_title": "Microsoft Surface Pro 7 (VDH-00003) Intel Core i3",
        "price": 6600,
        "stock": null,
        "last_update": "03/10/2025",
        "offer_url": "https://primini.ma/gotostore/636ae8ed607b93efb4379ac1?clickarea=retailer&pagetype=product"
      },
      {
        "store_name": "eDose",
        "store_url": "https://primini.ma/r/d/103/E-Dose",
        "store_rating": 0,
        "product_title": "MICROSOFT Surface Pro 7 – Intel Core i3",
        "price": 6799,
        "stock": null,
        "last_update": "03/10/2025",
        "offer_url": "https://primini.ma/gotostore/65d6fc42e656473d056f0331?clickarea=retailer&pagetype=product"
      }
    ],
    "offers_count": 2
  },
  {
    "name": "HP 7 Plus 1301 8 Go 17,8 cm (7\") Allwinner 1 Go Wi-Fi 4 (802.11n) Android Argent",
    "price": 1449,
    "offers": 2,
    "url": "https://primini.ma/c/p/142357/Hp-7-Plus-1301-8-Go-17-8-Cm-7-Allwinner-1-Go-Wi-Fi-4-802-11n-Android-Argent",
    "image": "https://cdn.primini.ma/250_0888182747650-hp-7-plus-1301-8-go-17-8-cm-7-allwinner-1-go-wi-fi-4-802-11n-android-argent-1.webp",
    "offers_details": [
      {
        "store_name": "Technoplace",
        "store_url": "https://primini.ma/r/d/1/Technoplace",
        "store_rating": 0,
        "product_title": "G4B64AA HP 7 Plus 1301 Tablet ARM Cort",
        "price": 1550.36,
        "stock": null,
        "last_update": "03/10/2025",
        "offer_url": "https://primini.ma/gotostore/65d925c7472ca713907df86b?clickarea=retailer&pagetype=product"
      }
    ],
    "offers_count": 1
  },
  {
    "name": "ASUS Fonepad 7 FE170CG-1A038A 3G 4 Go 17,8 cm (7\") Intel Atom® 1 Go Wi-Fi 4 (802.11n) Android Noir",
    "price": 1488,
    "offers": 2,
    "url": "https://primini.ma/c/p/138853/Asus-Fonepad-7-Fe170cg-1a038a-3g-4-Go-17-8-Cm-7-Intel-Atom-R-1-Go-Wi-Fi-4-802-11n-Android-Noir",
    "image": "https://cdn.primini.ma/250_asus-fonepad-7-fe170cg-1a038a-3g-4-go-17-8-cm-7-intel-atom-r-1-go-wi-fi-4-802-11n-android-noir-1.webp",
    "offers_details": [],
    "offers_count": 0
  },
  {
    "name": "Apple iPad Pro 5G TD-LTE & FDD-LTE 128 Go 32,8 cm (12.9\") Apple M 8 Go Wi-Fi 6E (802.11ax) iPadOS 16 Argent",
    "price": 15190,
    "offers": 2,
    "url": "https://primini.ma/c/p/168634/Apple-I-Pad-Pro-5g-Td-Lte-Fdd-Lte-128-Go-32-8-Cm-12-9-Apple-M-8-Go-Wi-Fi-6e-802-11ax-I-Pad-Os-16-Argent",
    "image": "https://cdn.primini.ma/250_0194253253440-apple-i-pad-pro-5g-td-lte-fdd-lte-128-go-32-8-cm-12-9-apple-m-8-go-wi-fi-6e-802-11ax-i-pad-os-16-argent-1.webp",
    "offers_details": [],
    "offers_count": 0
  },
  {
    "name": "Apple iPad Pro 128 Go Apple M 8 Go Argent",
    "price": 12990,
    "offers": 2,
    "url": "https://primini.ma/c/p/154464/Apple-I-Pad-Pro-128-Go-Apple-M-8-Go-Argent",
    "image": "https://cdn.primini.ma/250_0194253264897-apple-i-pad-pro-128-go-apple-m-8-go-argent-1.webp",
    "offers_details": [
      {
        "store_name": "VIRGIN MEGASTORE",
        "store_url": "https://primini.ma/r/d/82/Virgin-Megastore",
        "store_rating": 0,
        "product_title": "iPad Pro 11-Inch Wi-Fi 128Go - Silver",
        "price": 12990,
        "stock": null,
        "last_update": "03/10/2025",
        "offer_url": "https://primini.ma/gotostore/646c1f59fe1b293d801a816a?clickarea=retailer&pagetype=product"
      }
    ],
    "offers_count": 1
  },
  {
    "name": "Apple iPad Pro 256 Go Apple M 8 Go Gris",
    "price": 12790,
    "offers": 2,
    "url": "https://primini.ma/c/p/154495/Apple-I-Pad-Pro-256-Go-Apple-M-8-Go-Gris",
    "image": "https://cdn.primini.ma/250_0194253265160-apple-i-pad-pro-256-go-apple-m-8-go-gris-1.webp",
    "offers_details": [
      {
        "store_name": "VIRGIN MEGASTORE",
        "store_url": "https://primini.ma/r/d/82/Virgin-Megastore",
        "store_rating": 0,
        "product_title": "iPad Pro 11-Inch Wi-Fi 256Go - Space Grey",
        "price": 14690,
        "stock": null,
        "last_update": "03/10/2025",
        "offer_url": "https://primini.ma/gotostore/666a1dea624098261afd2fcb?clickarea=retailer&pagetype=product"
      }
    ],
    "offers_count": 1
  },
  {
    "name": "Apple iPad Pro 5G LTE 1 To Apple M 16 Go Gris",
    "price": 24290,
    "offers": 2,
    "url": "https://primini.ma/c/p/157214/Apple-I-Pad-Pro-5g-Lte-1-To-Apple-M-16-Go-Gris",
    "image": "https://cdn.primini.ma/250_0194253278283-apple-i-pad-pro-5g-lte-1-to-apple-m-16-go-gris-1.webp",
    "offers_details": [
      {
        "store_name": "Fournipro.ma",
        "store_url": "https://primini.ma/r/d/7/Fournipro-Ma",
        "store_rating": 0,
        "product_title": "11-inch iPad Pro 11\" 16G 1TB Wi-Fi + Cellular - Space Grey (MNYJ3NF/A)",
        "price": 23650,
        "stock": null,
        "last_update": "03/10/2025",
        "offer_url": "https://primini.ma/gotostore/655b8939bbb799cdbe7ce2fe?clickarea=retailer&pagetype=product"
      },
      {
        "store_name": "Micromad",
        "store_url": "https://primini.ma/r/d/87/Micromad",
        "store_rating": 0,
        "product_title": "iPad Pro 11 Pouces (Puce M2) - Tablette - MICROMAD #1 Boutique Hightech",
        "price": 26719,
        "stock": null,
        "last_update": "03/10/2025",
        "offer_url": "https://primini.ma/gotostore/659a889d5ed242f557cb9f5a?clickarea=retailer&pagetype=product"
      }
    ],
    "offers_count": 2
  },
  {
    "name": "Apple iPad 9th generation 10.2\" 64 Go Gris",
    "price": 4090,
    "offers": 2,
    "url": "https://primini.ma/c/p/119492/Apple-I-Pad-9th-Generation-10-2-64-Go-Gris",
    "image": "https://cdn.primini.ma/250_0194252515679-apple-i-pad-9th-generation-10-2-64-go-gris-1.webp",
    "offers_details": [],
    "offers_count": 0
  },
  {
    "name": "Apple iPad Pro 5G 128 Go Apple M 8 Go Gris",
    "price": 13350,
    "offers": 2,
    "url": "https://primini.ma/c/p/96629/Apple-I-Pad-Pro-5g-128-Go-Apple-M-8-Go-Gris",
    "image": "https://cdn.primini.ma/250_0194252203873-apple-i-pad-pro-5g-128-go-apple-m-8-go-gris-1.webp",
    "offers_details": [
      {
        "store_name": "VIRGIN MEGASTORE",
        "store_url": "https://primini.ma/r/d/82/Virgin-Megastore",
        "store_rating": 0,
        "product_title": "iPad Pro (2021) 11\" Wi-Fi + Cellular 128Go - Space Grey",
        "price": 13350,
        "stock": null,
        "last_update": "03/10/2025",
        "offer_url": "https://primini.ma/gotostore/666a1de7624098261afd2cc3?clickarea=retailer&pagetype=product"
      }
    ],
    "offers_count": 1
  },
  {
    "name": "Apple iPad Pro 5G 256 Go Apple M 8 Go Gris",
    "price": 14650,
    "offers": 2,
    "url": "https://primini.ma/c/p/84991/Apple-I-Pad-Pro-5g-256-Go-Apple-M-8-Go-Gris",
    "image": "https://cdn.primini.ma/250_0194252212226-apple-i-pad-pro-5g-256-go-apple-m-8-go-gris-1.webp",
    "offers_details": [
      {
        "store_name": "VIRGIN MEGASTORE",
        "store_url": "https://primini.ma/r/d/82/Virgin-Megastore",
        "store_rating": 0,
        "product_title": "iPad Pro (2021) 11\" Wi-Fi + Cellular 256Go - Space Grey",
        "price": 14650,
        "stock": null,
        "last_update": "03/10/2025",
        "offer_url": "https://primini.ma/gotostore/666a1de7624098261afd2cc5?clickarea=retailer&pagetype=product"
      }
    ],
    "offers_count": 1
  },
  {
    "name": "Apple iPad Air 64 Go 27,7 cm (10.9\") Bleu",
    "price": 7240,
    "offers": 2,
    "url": "https://primini.ma/c/p/83883/Apple-I-Pad-Air-64-Go-27-7-Cm-10-9-Bleu",
    "image": "https://cdn.primini.ma/250_0190199778153-apple-i-pad-air-64-go-27-7-cm-10-9-bleu-1.webp",
    "offers_details": [],
    "offers_count": 0
  },
  {
    "name": "Apple iPad Air 4G LTE 64 Go 27,7 cm (10.9\") Bleu",
    "price": 8590,
    "offers": 2,
    "url": "https://primini.ma/c/p/83882/Apple-I-Pad-Air-4g-Lte-64-Go-27-7-Cm-10-9-Bleu",
    "image": "https://cdn.primini.ma/250_0190199789715-apple-i-pad-air-4g-lte-64-go-27-7-cm-10-9-bleu-1.webp",
    "offers_details": [
      {
        "store_name": "VIRGIN MEGASTORE",
        "store_url": "https://primini.ma/r/d/82/Virgin-Megastore",
        "store_rating": 0,
        "product_title": "iPad Air (2020) 10.9\" Wi-Fi + Cellular 64 Go - Sky Blue",
        "price": 9200,
        "stock": null,
        "last_update": "03/10/2025",
        "offer_url": "https://primini.ma/gotostore/666a1de5624098261afd2be2?clickarea=retailer&pagetype=product"
      }
    ],
    "offers_count": 1
  },
  {
    "name": "Microsoft Surface Pro 8 Demo 512 Go 33 cm (13\") 16 Go Windows 11 Pro Platine",
    "price": 21990,
    "offers": 3,
    "url": "https://primini.ma/c/p/154576/Microsoft-Surface-Pro-8-Demo-512-Go-33-Cm-13-16-Go-Windows-11-Pro-Platine",
    "image": "https://cdn.primini.ma/250_0889842804881-microsoft-surface-pro-8-demo-512-go-33-cm-13-16-go-windows-11-pro-platine-1.webp",
    "offers_details": [
      {
        "store_name": "DistriComputer",
        "store_url": "https://primini.ma/r/d/32/Distri-Computer",
        "store_rating": 0,
        "product_title": "MICROSOFT SURFACE PRO 8 I7-16GB-512GBSSD-WIN10 PRO +Clavier+Stylet+Souris",
        "price": 27800,
        "stock": null,
        "last_update": "03/10/2025",
        "offer_url": "https://primini.ma/gotostore/65df40acb79534345659bfcc?clickarea=retailer&pagetype=product"
      }
    ],
    "offers_count": 1
  },
  {
    "name": "Microsoft Surface Pro 8 Demo 1 To 33 cm (13\") 32 Go Windows 11 Pro Platine",
    "price": 29390,
    "offers": 2,
    "url": "https://primini.ma/c/p/155144/Microsoft-Surface-Pro-8-Demo-1-To-33-Cm-13-32-Go-Windows-11-Pro-Platine",
    "image": "https://cdn.primini.ma/250_0889842805307-microsoft-surface-pro-8-demo-1-to-33-cm-13-32-go-windows-11-pro-platine-1.webp",
    "offers_details": [
      {
        "store_name": "DistriComputer",
        "store_url": "https://primini.ma/r/d/32/Distri-Computer",
        "store_rating": 0,
        "product_title": "MICROSOFT SURFACE PRO 8 I7-32GB-1TBSSD-WIN10 PRO +Clavier+Stylet+Souris",
        "price": 29390,
        "stock": null,
        "last_update": "03/10/2025",
        "offer_url": "https://primini.ma/gotostore/65df40adb79534345659c133?clickarea=retailer&pagetype=product"
      }
    ],
    "offers_count": 1
  },
  {
    "name": "Apple iPad 4G LTE 256 Go 25,9 cm (10.2\") Argent",
    "price": 7390,
    "offers": 3,
    "url": "https://primini.ma/c/p/154557/Apple-I-Pad-4g-Lte-256-Go-25-9-Cm-10-2-Argent",
    "image": "https://cdn.primini.ma/250_0194252522349-apple-i-pad-4g-lte-256-go-25-9-cm-10-2-argent-1.webp",
    "offers_details": [
      {
        "store_name": "Fournipro.ma",
        "store_url": "https://primini.ma/r/d/7/Fournipro-Ma",
        "store_rating": 0,
        "product_title": "IPAD (9ᵉ GÉNÉRATION), ÉCRAN RETINA 10,2″, PUCE A13 BIONIC, WI‑FI + CELLULAR 256 GO (MK4H3NF/A)",
        "price": 7490,
        "stock": null,
        "last_update": "03/10/2025",
        "offer_url": "https://primini.ma/gotostore/6752277270b0c9c2ef673919?clickarea=retailer&pagetype=product"
      },
      {
        "store_name": "VIRGIN MEGASTORE",
        "store_url": "https://primini.ma/r/d/82/Virgin-Megastore",
        "store_rating": 0,
        "product_title": "iPad 10.2\" - Inch WI-FI + Cellular 256 Go - Silver",
        "price": 9790,
        "stock": null,
        "last_update": "03/10/2025",
        "offer_url": "https://primini.ma/gotostore/666a1de7624098261afd2d31?clickarea=retailer&pagetype=product"
      }
    ],
    "offers_count": 2
  },
  {
    "name": "Tablette Huawei MatePad T 8 Bleu profond",
    "price": 1349,
    "offers": 2,
    "url": "https://primini.ma/c/p/80092/Tablette-Huawei-Mate-Pad-T-8-Bleu-Profond",
    "image": "https://primini.ma/images/placeholder.jpg",
    "offers_details": [
      {
        "store_name": "VIRGIN MEGASTORE",
        "store_url": "https://primini.ma/r/d/82/Virgin-Megastore",
        "store_rating": 0,
        "product_title": "Tablette MatePad T8 2Go 32Go - Bleu",
        "price": 1590,
        "stock": null,
        "last_update": "03/10/2025",
        "offer_url": "https://primini.ma/gotostore/666a1de9624098261afd2f09?clickarea=retailer&pagetype=product"
      }
    ],
    "offers_count": 1
  },
  {
    "name": "Apple iPad 32 Go 25,9 cm (10.2\") 3 Go iPadOS Gris",
    "price": 4290,
    "offers": 2,
    "url": "https://primini.ma/c/p/64353/Apple-I-Pad-32-Go-25-9-Cm-10-2-3-Go-I-Pad-Os-Gris",
    "image": "https://cdn.primini.ma/250_0190199807099-apple-i-pad-32-go-25-9-cm-10-2-3-go-i-pad-os-gris-1.webp",
    "offers_details": [],
    "offers_count": 0
  },
  {
    "name": "Tablette SAMSUNG TAB A 8\"4G - Noir (",
    "price": 1774,
    "offers": 5,
    "url": "https://primini.ma/c/p/63631/Tablette-Samsung-Tab-A-8-4g-Noir",
    "image": "https://cdn.primini.ma/250_8806090031588-tablette-samsung-tab-a-8-4g-noir-1.webp",
    "offers_details": [
      {
        "store_name": "Fournipro.ma",
        "store_url": "https://primini.ma/r/d/7/Fournipro-Ma",
        "store_rating": 0,
        "product_title": "TABLETTE SAMSUNG GALAXY TAB A SM-T295 8\" 32GB NOIR",
        "price": 1479,
        "stock": null,
        "last_update": "03/10/2025",
        "offer_url": "https://primini.ma/gotostore/670eea69f1eaac8a0f95691d?clickarea=retailer&pagetype=product"
      },
      {
        "store_name": "Iris.ma",
        "store_url": "https://primini.ma/r/d/3/Iris",
        "store_rating": 5,
        "product_title": "Tablette tactile Samsung Galaxy Tab A SM-T295 8&quot; (2019)",
        "price": 1700,
        "stock": null,
        "last_update": "03/10/2025",
        "offer_url": "https://primini.ma/gotostore/65dbc81b867c060a3f40ade8?clickarea=retailer&pagetype=product"
      },
      {
        "store_name": "Technoplace",
        "store_url": "https://primini.ma/r/d/1/Technoplace",
        "store_rating": 0,
        "product_title": "SAMSUNG TAB A SM-T295 8\" QUAD 2 Ghz 2GB / 32Go",
        "price": 1800,
        "stock": null,
        "last_update": "03/10/2025",
        "offer_url": "https://primini.ma/gotostore/65d925ca472ca713907dfc06?clickarea=retailer&pagetype=product"
      }
    ],
    "offers_count": 3
  },
  {
    "name": "Tablette Samsung Galaxy Tab A7 10.4\" (",
    "price": 2770,
    "offers": 3,
    "url": "https://primini.ma/c/p/60806/Tablette-Samsung-Galaxy-Tab-A7-10-4",
    "image": "https://primini.ma/images/placeholder.jpg",
    "offers_details": [
      {
        "store_name": "Iris.ma",
        "store_url": "https://primini.ma/r/d/3/Iris",
        "store_rating": 5,
        "product_title": "Tablette 4G Samsung Galaxy Tab A7 LTE (SM-T505)",
        "price": 2770,
        "stock": null,
        "last_update": "03/10/2025",
        "offer_url": "https://primini.ma/gotostore/65cd473b7faa7be215ba81a9?clickarea=retailer&pagetype=product"
      },
      {
        "store_name": "Pure Solutions",
        "store_url": "https://primini.ma/r/d/28/Pure-Solutions",
        "store_rating": 0,
        "product_title": "Tablette 4G Samsung Galaxy Tab A7 LTE Gris (SM-T505NZDDMWD)",
        "price": 2772,
        "stock": null,
        "last_update": "03/10/2025",
        "offer_url": "https://primini.ma/gotostore/6355c701b7872209484d50d6?clickarea=retailer&pagetype=product"
      },
      {
        "store_name": "Electromall",
        "store_url": "https://primini.ma/r/d/36/Electromall",
        "store_rating": 0,
        "product_title": "Samsung Galaxy Tab A7 10,4 3Go 32Go SILVER (SM-T505NZSDMWD)",
        "price": 2848,
        "stock": null,
        "last_update": "03/10/2025",
        "offer_url": "https://primini.ma/gotostore/6355db2ef5dfed72799c9e39?clickarea=retailer&pagetype=product"
      }
    ],
    "offers_count": 3
  },
  {
    "name": "Microsoft Surface Pro 7+ Demo 256 Go 31,2 cm (12.3\") 16 Go Windows 10 Pro Platine",
    "price": 21890,
    "offers": 2,
    "url": "https://primini.ma/c/p/155145/Microsoft-Surface-Pro-7-Demo-256-Go-31-2-Cm-12-3-16-Go-Windows-10-Pro-Platine",
    "image": "https://cdn.primini.ma/250_0889842665352-microsoft-surface-pro-7-demo-256-go-31-2-cm-12-3-16-go-windows-10-pro-platine-1.webp",
    "offers_details": [
      {
        "store_name": "DistriComputer",
        "store_url": "https://primini.ma/r/d/32/Distri-Computer",
        "store_rating": 0,
        "product_title": "MICROSOFT SURFACE PRO 7+ I7-16GB-256GBSSD-WIN10 PRO +Clavier+Stylet+Souris",
        "price": 21890,
        "stock": null,
        "last_update": "03/10/2025",
        "offer_url": "https://primini.ma/gotostore/64118b123548b3f820d91c24?clickarea=retailer&pagetype=product"
      }
    ],
    "offers_count": 1
  },
  {
    "name": "Microsoft Surface Pro 7+ Demo 512 Go 31,2 cm (12.3\") 16 Go Windows 10 Pro Platine",
    "price": 23150,
    "offers": 2,
    "url": "https://primini.ma/c/p/155146/Microsoft-Surface-Pro-7-Demo-512-Go-31-2-Cm-12-3-16-Go-Windows-10-Pro-Platine",
    "image": "https://cdn.primini.ma/250_0889842665635-microsoft-surface-pro-7-demo-512-go-31-2-cm-12-3-16-go-windows-10-pro-platine-1.webp",
    "offers_details": [
      {
        "store_name": "DistriComputer",
        "store_url": "https://primini.ma/r/d/32/Distri-Computer",
        "store_rating": 0,
        "product_title": "MICROSOFT SURFACE PRO 7+ I7-16GB-512GBSSD-WIN10 PRO +Clavier+Stylet+Souris",
        "price": 23150,
        "stock": null,
        "last_update": "03/10/2025",
        "offer_url": "https://primini.ma/gotostore/64118b123548b3f820d91c23?clickarea=retailer&pagetype=product"
      }
    ],
    "offers_count": 1
  },
  {
    "name": "Tablette Samsung Galaxy Tab S6 Lite- 10.4\" - 4G",
    "price": 129,
    "offers": 4,
    "url": "https://primini.ma/c/p/27574/Tablette-Samsung-Galaxy-Tab-S6-Lite-10-4-4g",
    "image": "https://primini.ma/images/placeholder.jpg",
    "offers_details": [
      {
        "store_name": "VIRGIN MEGASTORE",
        "store_url": "https://primini.ma/r/d/82/Virgin-Megastore",
        "store_rating": 0,
        "product_title": "Coque Book pour Galaxy Tab S6 Lite P615 -Silver",
        "price": 549,
        "stock": null,
        "last_update": "03/10/2025",
        "offer_url": "https://primini.ma/gotostore/6645d5031c30869f93b4d9b3?clickarea=retailer&pagetype=product"
      },
      {
        "store_name": "Pure Solutions",
        "store_url": "https://primini.ma/r/d/28/Pure-Solutions",
        "store_rating": 0,
        "product_title": "Tablette tactile Samsung Galaxy Tab S6 Lite 10,4 Blue (SM-P615NZAAMWD)",
        "price": 4026,
        "stock": null,
        "last_update": "03/10/2025",
        "offer_url": "https://primini.ma/gotostore/6355c700b7872209484d4f56?clickarea=retailer&pagetype=product"
      },
      {
        "store_name": "Iris.ma",
        "store_url": "https://primini.ma/r/d/3/Iris",
        "store_rating": 5,
        "product_title": "Tablette tactile Samsung Galaxy Tab S6 Lite 10,4\"",
        "price": 5669,
        "stock": null,
        "last_update": "03/10/2025",
        "offer_url": "https://primini.ma/gotostore/6351a3f755f61019978c63d2?clickarea=retailer&pagetype=product"
      }
    ],
    "offers_count": 3
  },
  {
    "name": "Apple iPad 4G LTE 32 Go 25,9 cm (10.2\") iPadOS Gris",
    "price": 5790,
    "offers": 2,
    "url": "https://primini.ma/c/p/20027/Apple-I-Pad-4g-Lte-32-Go-25-9-Cm-10-2-I-Pad-Os-Gris",
    "image": "https://cdn.primini.ma/250_0190199248618-apple-i-pad-4g-lte-32-go-25-9-cm-10-2-i-pad-os-gris-1.webp",
    "offers_details": [],
    "offers_count": 0
  },
  {
    "name": "Microsoft Surface Pro X 4G LTE 256 Go 33 cm (13\") 16 Go Windows 10 Home Platine",
    "price": 18100,
    "offers": 2,
    "url": "https://primini.ma/c/p/160331/Microsoft-Surface-Pro-X-4g-Lte-256-Go-33-Cm-13-16-Go-Windows-10-Home-Platine",
    "image": "https://cdn.primini.ma/250_0889842686524-microsoft-surface-pro-x-4g-lte-256-go-33-cm-13-16-go-windows-10-home-platine-1.webp",
    "offers_details": [
      {
        "store_name": "Micromad",
        "store_url": "https://primini.ma/r/d/87/Micromad",
        "store_rating": 0,
        "product_title": "Microsoft Surface Pro X - Tablette - MICROMAD #1 Boutique Hightech",
        "price": 19910,
        "stock": null,
        "last_update": "03/10/2025",
        "offer_url": "https://primini.ma/gotostore/659a889c5ed242f557cb9dcf?clickarea=retailer&pagetype=product"
      }
    ],
    "offers_count": 1
  },
  {
    "name": "Microsoft Surface Pro 7 256 Go 31,2 cm (12.3\") 8 Go Windows 10 Home Platine",
    "price": 16788,
    "offers": 2,
    "url": "https://primini.ma/c/p/155151/Microsoft-Surface-Pro-7-256-Go-31-2-Cm-12-3-8-Go-Windows-10-Home-Platine",
    "image": "https://cdn.primini.ma/250_0889842481891-microsoft-surface-pro-7-256-go-31-2-cm-12-3-8-go-windows-10-home-platine-1.webp",
    "offers_details": [
      {
        "store_name": "DistriComputer",
        "store_url": "https://primini.ma/r/d/32/Distri-Computer",
        "store_rating": 0,
        "product_title": "MICROSOFT SURFACE PRO 7 I5-8GB-256GBSSD-WIN10 HOME+Clavier+Stylet+Souris",
        "price": 17200,
        "stock": null,
        "last_update": "03/10/2025",
        "offer_url": "https://primini.ma/gotostore/64118b123548b3f820d91c1a?clickarea=retailer&pagetype=product"
      }
    ],
    "offers_count": 1
  },
  {
    "name": "Apple iPad Air 2 128 Go 2 Go iOS Argent",
    "price": 8490,
    "offers": 2,
    "url": "https://primini.ma/c/p/155431/Apple-I-Pad-Air-2-128-Go-2-Go-I-Os-Argent",
    "image": "https://cdn.primini.ma/250_0888462026161-apple-i-pad-air-2-128-go-2-go-i-os-argent-1.webp",
    "offers_details": [
      {
        "store_name": "Fournipro.ma",
        "store_url": "https://primini.ma/r/d/7/Fournipro-Ma",
        "store_rating": 0,
        "product_title": "Tablette Apple APPLE iPad Air 2 9,7'' WiFi 128 Go",
        "price": 7075,
        "stock": null,
        "last_update": "03/10/2025",
        "offer_url": "https://primini.ma/gotostore/635aa3de6cc4d0321e8e7cce?clickarea=retailer&pagetype=product"
      }
    ],
    "offers_count": 1
  }
]